{"actions": 7673, "added_lines": 270977.0, "added_lines_30": 262678, "added_lines_365": 6513944, "added_lines_7": 14677, "authors": 205, "authors_30": 22, "authors_365": 75, "authors_7": 4, "avg_commits_author": 9.6447, "avg_commits_month": 17.757, "avg_files_author": 10.3198, "avg_files_month": 19.0, "branches": 4, "commits": 1900, "commits_30": 34, "commits_365": 483, "commits_7": 2, "committers": 132, "diff_netadded_lines_30": 160733, "diff_netadded_lines_365": 3279376, "diff_netadded_lines_7": -17742, "diff_netauthors_30": 8, "diff_netauthors_365": 1, "diff_netauthors_7": -5, "diff_netcommits_30": -3, "diff_netcommits_365": 75, "diff_netcommits_7": -8, "diff_netfiles_30": -276, "diff_netfiles_365": 298, "diff_netfiles_7": -55, "diff_netremoved_lines_30": 58450, "diff_netremoved_lines_365": -61436, "diff_netremoved_lines_7": 37765, "files": 2033, "files_30": 80, "files_365": 869, "files_7": 2, "first_date": "2005-04-13", "last_date": "2014-08-26", "percentage_added_lines_30": 157, "percentage_added_lines_365": 101, "percentage_added_lines_7": 54, "percentage_authors_30": 57, "percentage_authors_365": 1, "percentage_authors_7": 55, "percentage_commits_30": 8, "percentage_commits_365": 18, "percentage_commits_7": 80, "percentage_files_30": 77, "percentage_files_365": 52, "percentage_files_7": 96, "percentage_removed_lines_30": 32, "percentage_removed_lines_365": 1, "percentage_removed_lines_7": 742, "removed_lines": 107032.0, "removed_lines_30": 240157, "removed_lines_365": 4167532, "removed_lines_7": 42849, "repositories": 1}