{"diff_netsenders_30": 9, "diff_netsenders_365": -39, "diff_netsenders_7": 4, "diff_netsent_30": -13, "diff_netsent_365": 255, "diff_netsent_7": 12, "first_date": "2005-10-22", "last_date": "2014-08-29", "percentage_senders_30": 26, "percentage_senders_365": 20, "percentage_senders_7": 44, "percentage_sent_30": 7, "percentage_sent_365": 19, "percentage_sent_7": 92, "repositories": 1, "senders": 675, "senders_30": 43, "senders_365": 148, "senders_7": 13, "senders_init": 522, "senders_response": 526, "sent": 25074, "sent_30": 161, "sent_365": 1568, "sent_7": 25, "sent_response": 17498, "threads": 13632}