{"diff_netsenders_30": -2, "diff_netsenders_365": 5, "diff_netsenders_7": 2, "diff_netsent_30": -39, "diff_netsent_365": 2, "diff_netsent_7": 2, "first_date": "2005-10-22", "last_date": "2014-09-04", "percentage_senders_30": 18, "percentage_senders_365": 20, "percentage_senders_7": 0, "percentage_sent_30": 76, "percentage_sent_365": 1, "percentage_sent_7": 0, "repositories": 1, "senders": 67, "senders_30": 9, "senders_365": 29, "senders_7": 2, "senders_init": 55, "senders_response": 57, "sent": 575, "sent_30": 12, "sent_365": 142, "sent_7": 2, "sent_response": 455, "threads": 365}