{"diff_netsenders_30": -3, "diff_netsenders_365": 73, "diff_netsenders_7": -3, "diff_netsent_30": -87, "diff_netsent_365": 1074, "diff_netsent_7": -23, "first_date": "2005-10-22", "last_date": "2014-08-07", "percentage_senders_30": 23, "percentage_senders_365": 0, "percentage_senders_7": 42, "percentage_sent_30": 64, "percentage_sent_365": 0, "percentage_sent_7": 74, "repositories": 1, "senders": 73, "senders_30": 10, "senders_365": 73, "senders_7": 4, "senders_init": 51, "senders_response": 66, "sent": 1074, "sent_30": 48, "sent_365": 1074, "sent_7": 8, "sent_response": 890, "threads": 783}