{"allhistory_participants":229,"tickets":2844,"opened":2844,"openers":138,"first_date":"2012-08-30","last_date":"2014-02-04","closers":63,"closed":1212,"changers":134,"changed":2409,"url":"https://tickets.puppetlabs.com/browse/ENTERPRISE","type":"jira","repositories":13,"diff_netclosed_365":1212,"percentage_closed_365":"NA","diff_netclosed_30":14,"percentage_closed_30":4,"diff_netclosed_7":21,"percentage_closed_7":31,"diff_netopened_365":2838,"percentage_opened_365":94600,"diff_netopened_30":-599,"percentage_opened_30":58,"diff_netopened_7":45,"percentage_opened_7":54,"diff_netclosers_7":-3,"percentage_closers_7":15,"diff_netclosers_30":12,"percentage_closers_30":38,"diff_netclosers_365":63,"percentage_closers_365":"NA","diff_netchangers_7":0,"percentage_changers_7":0,"diff_netchangers_30":31,"percentage_changers_30":45,"diff_netchangers_365":134,"percentage_changers_365":"NA","opened_7":131,"closed_7":87,"closers_7":17,"changers_7":42,"opened_14":209,"closed_14":152,"closers_14":26,"changers_14":57,"opened_30":432,"closed_30":316,"closers_30":43,"changers_30":99,"opened_60":1467,"closed_60":605,"closers_60":54,"changers_60":121,"opened_90":1888,"closed_90":758,"closers_90":55,"changers_90":123,"opened_180":2616,"closed_180":1088,"closers_180":61,"changers_180":130,"opened_365":2841,"closed_365":1212,"closers_365":63,"changers_365":134,"opened_730":2844,"closed_730":1212,"closers_730":63,"changers_730":134}