{"allhistory_participants":173,"tickets":2149,"opened":2149,"openers":102,"first_date":"2013-05-28","last_date":"2014-01-18","closers":56,"closed":850,"changers":107,"changed":1730,"url":"https://tickets.puppetlabs.com/browse/ENTERPRISE","type":"jira","repositories":13,"diff_netclosed_365":850,"percentage_closed_365":"NA","diff_netclosed_30":1,"percentage_closed_30":0,"diff_netclosed_7":-65,"percentage_closed_7":61,"diff_netopened_365":2149,"percentage_opened_365":"NA","diff_netopened_30":-697,"percentage_opened_30":71,"diff_netopened_7":25,"percentage_opened_7":28,"diff_netclosers_7":-11,"percentage_closers_7":47,"diff_netclosers_30":6,"percentage_closers_30":24,"diff_netclosers_365":56,"percentage_closers_365":"NA","diff_netchangers_7":-16,"percentage_changers_7":29,"diff_netchangers_30":25,"percentage_changers_30":45,"diff_netchangers_365":107,"percentage_changers_365":"NA","opened_7":114,"closed_7":40,"closers_7":12,"changers_7":40,"opened_14":202,"closed_14":139,"closers_14":29,"changers_14":71,"opened_30":276,"closed_30":157,"closers_30":31,"changers_30":81,"opened_60":1247,"closed_60":301,"closers_60":41,"changers_60":94,"opened_90":1471,"closed_90":433,"closers_90":48,"changers_90":96,"opened_180":1961,"closed_180":747,"closers_180":55,"changers_180":106,"opened_365":2152,"closed_365":850,"closers_365":56,"changers_365":108,"opened_730":2152,"closed_730":850,"closers_730":56,"changers_730":108}