{"allhistory_participants": 548, "changed": 4292, "changers": 277, "closed": 1369, "closed_14": 105, "closed_180": 1228, "closed_30": 170, "closed_365": 1369, "closed_60": 545, "closed_7": 39, "closed_730": 1369, "closed_90": 786, "closers": 76, "closers_14": 17, "closers_180": 71, "closers_30": 26, "closers_365": 76, "closers_60": 43, "closers_7": 13, "closers_730": 76, "closers_90": 59, "diff_netchangers_30": -25, "diff_netchangers_365": 277, "diff_netchangers_7": 10, "diff_netclosed_30": -210, "diff_netclosed_365": 1369, "diff_netclosed_7": -27, "diff_netclosers_30": -8, "diff_netclosers_365": 76, "diff_netclosers_7": 4, "diff_netopened_30": -23, "diff_netopened_365": 4454, "diff_netopened_7": -3, "first_date": "2011-06-28", "last_date": "2014-04-09", "opened": 4464, "opened_14": 189, "opened_180": 3710, "opened_30": 476, "opened_365": 4458, "opened_60": 976, "opened_7": 93, "opened_730": 4462, "opened_90": 1621, "openers": 376, "percentage_changers_30": 20, "percentage_changers_365": 0, "percentage_changers_7": 23, "percentage_closed_30": 55, "percentage_closed_365": 0, "percentage_closed_7": 40, "percentage_closers_30": 23, "percentage_closers_365": 0, "percentage_closers_7": 44, "percentage_opened_30": 4, "percentage_opened_365": 111350, "percentage_opened_7": 3, "trackers": 13, "type": "jira", "url": "https://tickets.puppetlabs.com/browse/ENTERPRISE"}