{"diff_netsenders_30": -15, "diff_netsenders_365": -142, "diff_netsenders_7": 23, "diff_netsent_30": -58, "diff_netsent_365": -2073, "diff_netsent_7": 74, "first_date": "2005-10-22", "last_date": "2014-07-16", "percentage_senders_30": 5, "percentage_senders_365": 7, "percentage_senders_7": 31, "percentage_sent_30": 5, "percentage_sent_365": 14, "percentage_sent_7": 48, "repositories": 5, "senders": 5386, "senders_30": 247, "senders_365": 1662, "senders_7": 95, "senders_init": 4467, "senders_response": 4007, "sent": 92870, "sent_30": 939, "sent_365": 12029, "sent_7": 228, "sent_response": 69971, "threads": 56442}