{"diff_netsenders_30": -6, "diff_netsenders_365": -214, "diff_netsenders_7": -12, "diff_netsent_30": 61, "diff_netsent_365": -814, "diff_netsent_7": -20, "first_date": "2005-10-22", "last_date": "2014-10-25", "percentage_senders_30": 2, "percentage_senders_365": 11, "percentage_senders_7": 13, "percentage_sent_30": 7, "percentage_sent_365": 6, "percentage_sent_7": 11, "repositories": 5, "senders": 5867, "senders_30": 238, "senders_365": 1580, "senders_7": 74, "senders_init": 4879, "senders_response": 4330, "sent": 95744, "sent_30": 896, "sent_365": 11857, "sent_7": 155, "sent_response": 72162, "threads": 58244}