{"senders.":{"id":[50,3506,51,61,40,1066,4707,76,22,316,216,176,75,3,2536,4663,312,382,26,5,1,311,257,5889,4347,338,10,3382,77,20,1114,2484,207,541,5686,218,72,3820,3589,2825,3597,66,3923,6,881,625,42,199,2631,1737],"senders":["Luke Kanies","jcbollinger","James Turnbull","Nigel Kersten","R.I.Pienaar","Brice Figureau","puppet","Daniel Pittman","David Schmitt","duritong","Felix Frank","Ohad Levy","Markus Roberts","Jeff McCune","Douglas","Trevor Vaughan","David Lutterkort","Patrick Carlisle","Nan Liu","Dan Bode","Ken Barber","Paul Nasrat","Henrik Lindberg","Ygor","Matthew Palmer","Stefan Schulte","Andrew Parker","Jesse A Wolfe","Jacob Helwig","Josh Cooper","markus","Digant C Kasundra","Matt Robinson","Paul Lathrop","denmat","Paul Berry","Todd Zullinger","Larry Ludwig","Jo Rhett","Ghislain ADNET","Jakov Sosic","Michael Stahnke","Mohamed Lrhazi","Matthaus Litteken","Scott Smith","Andrew Shafer","Nick Lewis","Michael DeHaan","Evan Hisey","Arnau Bria"],"sent":[7466,2307,2078,1890,1852,1665,1520,1215,1040,1028,960,874,805,773,689,678,641,629,560,492,474,462,449,438,417,408,397,393,382,374,364,355,339,333,324,304,304,297,293,292,292,292,290,287,269,267,265,260,252,250]},"senders.last year":{"id":[3506,216,40,76,10,5338,5889,257,1,64,27,20,3500,3559,4663,6,22,2979,302,50,312,3597,25,1179,1642,3854,26,3,29,112,233,44,4861,1800,746,883,4883,3751,268,3287,3702,862,4010,1384,37,23,3681,3088,4133,1547],"senders":["jcbollinger","Felix Frank","R.I.Pienaar","Daniel Pittman","Andrew Parker","Stuart Cracraft","Ygor","Henrik Lindberg","Ken Barber","Rob Reynolds","Erik Dal\u00e9n","Josh Cooper","Johan De Wit","Jose Luis Ledesma","Trevor Vaughan","Matthaus Litteken","David Schmitt","Ellison Marks","Jason Antman","Luke Kanies","David Lutterkort","Jakov Sosic","Gavin Williams","Peter Valdemar M\u00f8rch","Andreas Dvorak","Larry Fast","Nan Liu","Jeff McCune","Ashley Penney","Nikola Petrov","Eric Sorenson","Pieter Loubser","Rahul Khengare","Andriy Yurchuk","Alex Scoble","Alessandro Franceschi","Ramin K","Klavs Klavsen","Dustin J. Mitchell","Jeff Bachtel","Keith Burdis","Chris Portman","Maish Saidel-Keesing","daenney","Ryan Coleman","Adrien Thebo","kaustubh chaudhari","Harshita Sinha","Matthew Burgess","Andrew"],"sent":[772,267,265,215,206,185,184,150,143,128,105,104,97,90,87,87,87,79,78,72,69,68,62,59,57,56,56,55,55,54,53,51,51,51,50,50,50,50,49,47,46,46,45,45,45,44,43,43,43,42]},"senders.last month":{"id":[3506,10,4663,3500,3559,43,64,216,5926,1950,2182,1384,76,4515,22,3908,112,4133,3589,649,414,6,338,257,3689,2564,5726,1066,27,302,4015,23,26,3577,44,3681,2709,1432,67,27949,275,3,1483,1,20,2448,1473,883,4982,4809],"senders":["jcbollinger","Andrew Parker","Trevor Vaughan","Johan De Wit","Jose Luis Ledesma","Richard Clamp","Rob Reynolds","Felix Frank","zerozerounouno@gmail.com","bluethundr","Christopher Wood","daenney","Daniel Pittman","Jon Forrest","David Schmitt","Jay Benner","Nikola Petrov","Matthew Burgess","Jo Rhett","Craig Dunn","Melissa","Matthaus Litteken","Stefan Schulte","Henrik Lindberg","Kenton Brede","HPUX_PUPPET","valentino@thnkbig.com","Brice Figureau","Erik Dal\u00e9n","Jason Antman","Martin Alfke","Adrien Thebo","Nan Liu","jmp242","Pieter Loubser","kaustubh chaudhari","Jon Yeargers","George Brown","Moses Mendoza","Dirk Heinrichs","Kylo Ginsberg","Jeff McCune","Adam Winberg","Ken Barber","Josh Cooper","cko","Deep","Alessandro Franceschi","Rakesh K","Andy Spiegl"],"sent":[73,26,23,21,19,18,17,17,16,15,13,13,13,13,12,12,11,10,10,9,8,8,8,8,7,7,7,7,7,7,7,7,7,7,6,6,6,6,6,6,5,5,5,5,5,5,5,5,5,5]}}