{"diff_netsenders_30": -3, "diff_netsenders_365": -34, "diff_netsenders_7": -7, "diff_netsent_30": 37, "diff_netsent_365": -2831, "diff_netsent_7": -52, "first_date": "2005-10-22", "last_date": "2014-05-16", "percentage_senders_30": 1, "percentage_senders_365": 1, "percentage_senders_7": 7, "percentage_sent_30": 3, "percentage_sent_365": 19, "percentage_sent_7": 23, "repositories": 5, "senders": 5238, "senders_14": 148, "senders_180": 1006, "senders_30": 282, "senders_365": 1761, "senders_60": 471, "senders_7": 88, "senders_730": 3042, "senders_90": 616, "senders_init": 4343, "senders_response": 3899, "sent": 90929, "sent_14": 394, "sent_180": 6321, "sent_30": 1010, "sent_365": 11894, "sent_60": 1990, "sent_7": 170, "sent_730": 26771, "sent_90": 2937, "sent_response": 68494, "threads": 55217}