{"diff_netsenders_30": -145, "diff_netsenders_365": 32, "diff_netsenders_7": -23, "diff_netsent_30": -6246, "diff_netsent_365": -49448, "diff_netsent_7": -366, "first_date": "2007-12-02", "last_date": "2014-11-15", "percentage_senders_30": 13, "percentage_senders_365": 0, "percentage_senders_7": 7, "percentage_sent_30": 24, "percentage_sent_365": 16, "percentage_sent_7": 8, "repositories": 1, "senders": 19222, "senders_30": 929, "senders_365": 6007, "senders_7": 302, "sent": 1651495, "sent_30": 19247, "sent_365": 259559, "sent_7": 4006}