{"actions": 57580, "added_lines": 1670293.0, "added_lines_30": 1019547, "added_lines_365": 6256497, "added_lines_7": 290622, "authors": 404, "authors_30": 38, "authors_365": 157, "authors_7": 18, "avg_commits_author": 34.7, "avg_commits_month": 126.1818, "avg_files_author": 21.0475, "avg_files_month": 76.5364, "branches": 15, "commits": 13880, "commits_30": 237, "commits_365": 2896, "commits_7": 36, "committers": 268, "diff_netadded_lines_30": 533600, "diff_netadded_lines_365": 3346279, "diff_netadded_lines_7": -270310, "diff_netauthors_30": 6, "diff_netauthors_365": 33, "diff_netauthors_7": 5, "diff_netcommits_30": 51, "diff_netcommits_365": 903, "diff_netcommits_7": -36, "diff_netfiles_30": 77, "diff_netfiles_365": -442, "diff_netfiles_7": -77, "diff_netremoved_lines_30": 1054852, "diff_netremoved_lines_365": -247570, "diff_netremoved_lines_7": -662052, "files": 8419, "files_30": 381, "files_365": 2420, "files_7": 80, "first_date": "2005-04-13", "last_date": "2014-06-27", "percentage_added_lines_30": 109, "percentage_added_lines_365": 114, "percentage_added_lines_7": 48, "percentage_authors_30": 18, "percentage_authors_365": 26, "percentage_authors_7": 38, "percentage_commits_30": 27, "percentage_commits_365": 45, "percentage_commits_7": 50, "percentage_files_30": 25, "percentage_files_365": 15, "percentage_files_7": 49, "percentage_removed_lines_30": 557, "percentage_removed_lines_365": 6, "percentage_removed_lines_7": 70, "removed_lines": 1233282.0, "removed_lines_30": 1243971, "removed_lines_365": 3780740, "removed_lines_7": 281275, "repositories": 1}