{"diff_netsenders_30": 7, "diff_netsenders_365": 76, "diff_netsenders_7": 7, "diff_netsent_30": 486, "diff_netsent_365": 29263, "diff_netsent_7": 650, "first_date": "2010-10-29", "last_date": "2014-08-09", "percentage_senders_30": 10, "percentage_senders_365": 26, "percentage_senders_7": 22, "percentage_sent_30": 21, "percentage_sent_365": 123, "percentage_sent_7": 140, "repositories": 1, "senders": 702, "senders_30": 73, "senders_365": 363, "senders_7": 38, "sent": 87405, "sent_30": 2784, "sent_365": 52953, "sent_7": 1114}