{"actions": 313, "added_lines": 3899.0, "added_lines_30": 222433, "added_lines_365": 5846140, "added_lines_7": 21764, "authors": 17, "authors_30": 8, "authors_365": 11, "authors_7": 0, "avg_commits_author": 10.3077, "avg_commits_month": 5.5833, "avg_files_author": 4.6154, "avg_files_month": 2.5, "branches": 1, "commits": 134, "commits_30": 5, "commits_365": 69, "commits_7": 0, "committers": 17, "diff_netadded_lines_30": -4913, "diff_netadded_lines_365": 1824409, "diff_netadded_lines_7": 18903, "diff_netauthors_30": 1, "diff_netauthors_365": 1, "diff_netauthors_7": -2, "diff_netcommits_30": -10, "diff_netcommits_365": 31, "diff_netcommits_7": -1, "diff_netfiles_30": -17, "diff_netfiles_365": -4, "diff_netfiles_7": -2, "diff_netremoved_lines_30": 176506, "diff_netremoved_lines_365": -967292, "diff_netremoved_lines_7": -8397, "files": 60, "files_30": 5, "files_365": 34, "files_7": 0, "first_date": "2005-04-13", "last_date": "2014-10-01", "percentage_added_lines_30": 2, "percentage_added_lines_365": 45, "percentage_added_lines_7": 660, "percentage_authors_30": 14, "percentage_authors_365": 10, "percentage_authors_7": 100, "percentage_commits_30": 66, "percentage_commits_365": 81, "percentage_commits_7": 100, "percentage_files_30": 77, "percentage_files_365": 10, "percentage_files_7": 100, "percentage_removed_lines_30": 297, "percentage_removed_lines_365": 20, "percentage_removed_lines_7": 34, "removed_lines": 1948.0, "removed_lines_30": 235786, "removed_lines_365": 3798829, "removed_lines_7": 15898, "repositories": 1}