{"asenders": 490, "asenders_30": 53, "asenders_365": 391, "asenders_7": 22, "asent": 2023, "asent_30": 87, "asent_365": 1437, "asent_7": 30, "csenders": 587, "csenders_30": 32, "csenders_365": 463, "csenders_7": 12, "csent": 2671, "csent_30": 52, "csent_365": 1905, "csent_7": 18, "diff_netasenders_30": 10, "diff_netasenders_365": 236, "diff_netasenders_7": 11, "diff_netasent_30": 5, "diff_netasent_365": 851, "diff_netasent_7": 14, "diff_netcsenders_30": -24, "diff_netcsenders_365": 288, "diff_netcsenders_7": 5, "diff_netcsent_30": -64, "diff_netcsent_365": 1139, "diff_netcsent_7": 5, "diff_netparticipants_30": -9, "diff_netparticipants_365": 575, "diff_netparticipants_7": 13, "diff_netqsenders_30": -10, "diff_netqsenders_365": 484, "diff_netqsenders_7": 5, "diff_netqsent_30": 114, "diff_netqsent_365": 964, "diff_netqsent_7": 3, "init_date": "2012-10-26", "last_date": "2014-06-30", "participants": 1058, "participants_30": 107, "participants_365": 865, "participants_7": 40, "percentage_asenders_30": 23, "percentage_asenders_365": 152, "percentage_asenders_7": 100, "percentage_asent_30": 6, "percentage_asent_365": 145, "percentage_asent_7": 87, "percentage_csenders_30": 42, "percentage_csenders_365": 164, "percentage_csenders_7": 71, "percentage_csent_30": 55, "percentage_csent_365": 148, "percentage_csent_7": 38, "percentage_participants_30": 7, "percentage_participants_365": 198, "percentage_participants_7": 48, "percentage_qsenders_30": 12, "percentage_qsenders_365": 219, "percentage_qsenders_7": 26, "percentage_qsent_30": 122, "percentage_qsent_365": 251, "percentage_qsent_7": 9, "qsenders": 876, "qsenders_30": 73, "qsenders_365": 705, "qsenders_7": 24, "qsent": 1730, "qsent_30": 207, "qsent_365": 1347, "qsent_7": 34}