{"authors": 802, "authors_30": 134, "authors_365": 586, "authors_7": 40, "diff_netauthors_30": -19, "diff_netauthors_365": 276, "diff_netauthors_7": -12, "diff_netmodules_30": -3, "diff_netmodules_365": 454, "diff_netmodules_7": -2, "diff_netreleases_30": -95, "diff_netreleases_365": 3050, "diff_netreleases_7": -18, "init_date": "2010-05-20 22:43:19", "last_date": "2014-06-09 21:00:41", "modules": 2434, "modules_30": 89, "modules_365": 1259, "modules_7": 15, "percentage_authors_30": 12, "percentage_authors_365": 89, "percentage_authors_7": 23, "percentage_modules_30": 3, "percentage_modules_365": 56, "percentage_modules_7": 11, "percentage_releases_30": 18, "percentage_releases_365": 139, "percentage_releases_7": 16, "releases": 8198, "releases_30": 417, "releases_365": 5235, "releases_7": 94}