{"authors.": {"id": [658078, 657735, 657935, 657677, 658213, 657773, 657562, 658142, 657733, 657765, 658060, 657726, 658076, 658210, 657851, 657547, 657598, 658255, 657513, 657530, 658087, 658174, 658010, 658058, 657823, 657919, 657924, 658261, 658045, 657759, 657813, 658089, 658274, 658291, 658093, 658157, 657743, 657525, 657544, 657816, 658074, 657835, 657646, 657682, 657764, 657549, 657804, 657840, 657515, 658284], "releases": [547, 382, 327, 224, 207, 181, 171, 140, 138, 121, 111, 89, 83, 79, 77, 76, 68, 59, 58, 56, 56, 56, 53, 51, 51, 48, 48, 47, 42, 41, 40, 40, 40, 40, 39, 38, 37, 35, 35, 34, 33, 32, 31, 31, 31, 30, 30, 30, 30, 30], "username": ["puppetlabs", "example42", "maestrodev", "dhoppe", "thias", "ghoneycutt", "biemond", "saz", "evenup", "garethr", "pennycoders", "erwbgy", "ptomulik", "theforeman", "jhoblitt", "arusso", "camptocamp", "viirya", "adrien", "alkivi", "razorsedge", "skoblenick", "netmanagers", "pdxcat", "jamtur01", "leonardothibes", "llehmijo", "vlshch", "opentable", "fsalum", "inkblot", "rcoleman", "willdurand", "zleslie", "rendhalver", "seteam", "fiddyspence", "AlexCline", "arioch", "ispavailability", "proletaryo", "jbussdieker", "dalen", "dmexe", "gajdaw", "attachmentgenie", "huit", "jdowning", "Aethylred", "yguenane"]}, "authors.last month": {"id": [657764, 658078, 657773, 658255, 657733, 657735, 657935, 657795, 657851, 657878, 657562, 658045, 658071, 658213, 657500, 657515, 657518, 657598, 657628, 657856, 658209, 657606, 657630, 657913, 657915, 657922, 657940, 657972, 657980, 657998, 657999, 658147, 658182, 657552, 657584, 657666, 657719, 657759, 657832, 657840, 657971, 657975, 657990, 658049, 658124, 658186, 657544, 657566, 657589, 657625], "releases": [31, 27, 21, 15, 13, 12, 12, 10, 10, 10, 8, 7, 7, 7, 5, 5, 5, 5, 5, 5, 5, 4, 4, 4, 4, 4, 4, 4, 4, 4, 4, 4, 4, 3, 3, 3, 3, 3, 3, 3, 3, 3, 3, 3, 3, 3, 2, 2, 2, 2], "username": ["gajdaw", "puppetlabs", "ghoneycutt", "viirya", "evenup", "example42", "maestrodev", "hardening", "jhoblitt", "jriviere", "biemond", "opentable", "pnd", "thias", "aboe", "Aethylred", "aimonb", "camptocamp", "counsyl", "jlcox", "thbe", "CERNOps", "cprice404", "lbetz", "lcgdm", "lexance", "markea", "mjhas", "momer", "myDistro", "myoung34", "SchnWalter", "spantree", "badgerious", "BoxUpp", "deric", "engage", "fsalum", "jballou", "jdowning", "mjanser", "mlehner616", "msopentech", "oris", "rtyler", "srf", "arioch", "binarin", "brentschler", "conzar"]}, "authors.last year": {"id": [657735, 658078, 657935, 657562, 658060, 657773, 658213, 657733, 658076, 657851, 658142, 658210, 657530, 658174, 657919, 657765, 658261, 658255, 657547, 658045, 657813, 657598, 658010, 657544, 658274, 657835, 657764, 657915, 658184, 657515, 657793, 657840, 658232, 657584, 657743, 657769, 657500, 657804, 657940, 658058, 658070, 657682, 657911, 658192, 657625, 657972, 658074, 657497, 657667, 658157], "releases": [362, 287, 267, 135, 111, 107, 105, 101, 83, 66, 57, 57, 56, 56, 48, 47, 47, 46, 44, 42, 40, 39, 39, 35, 33, 32, 31, 29, 29, 28, 26, 26, 26, 25, 25, 25, 23, 23, 23, 23, 23, 22, 22, 22, 21, 21, 21, 20, 20, 20], "username": ["example42", "puppetlabs", "maestrodev", "biemond", "pennycoders", "ghoneycutt", "thias", "evenup", "ptomulik", "jhoblitt", "saz", "theforeman", "alkivi", "skoblenick", "leonardothibes", "garethr", "vlshch", "viirya", "arusso", "opentable", "inkblot", "camptocamp", "netmanagers", "arioch", "willdurand", "jbussdieker", "gajdaw", "lcgdm", "spuder", "Aethylred", "hajee", "jdowning", "tracywebtech", "BoxUpp", "fiddyspence", "gdsoperations", "aboe", "huit", "markea", "pdxcat", "pltraining", "dmexe", "KyleAnderson", "stankevich", "conzar", "mjhas", "proletaryo", "a2tar", "desalvo", "seteam"]}}