{"authors.": {"id": [2249092, 2249093, 2249095, 2249133, 2249103, 2249165, 2249156, 2249101, 2249173, 2249112, 2249270, 2249160, 2249150, 2249102, 2249278, 2249266, 2249180, 2249282, 2249149, 2249342, 2249148, 2249456, 2249352, 2249152, 2249118, 2249131, 2249121, 2249146, 2249192, 2249790, 2249169, 2249400, 2249138, 2249109, 2249262, 2249120, 2249181, 2249135, 2249124, 2249218, 2249123, 2249281, 2249376, 2249106, 2249208, 2249315, 2249242, 2249107, 2249401, 2249147], "releases": [627, 386, 373, 224, 211, 204, 199, 145, 143, 141, 111, 93, 90, 89, 83, 78, 77, 60, 59, 56, 56, 56, 55, 53, 53, 52, 51, 48, 48, 47, 45, 45, 44, 42, 42, 42, 41, 40, 39, 39, 38, 36, 36, 36, 35, 35, 35, 34, 34, 34], "username": ["puppetlabs", "example42", "maestrodev", "dhoppe", "thias", "ghoneycutt", "biemond", "saz", "evenup", "garethr", "pennycoders", "camptocamp", "theforeman", "erwbgy", "ptomulik", "jhoblitt", "arusso", "viirya", "adrien", "alkivi", "razorsedge", "skoblenick", "leonardothibes", "netmanagers", "opentable", "pdxcat", "jamtur01", "llehmijo", "zleslie", "vlshch", "arioch", "tracywebtech", "fsalum", "fiddyspence", "inkblot", "willdurand", "hajee", "rcoleman", "attachmentgenie", "rendhalver", "seteam", "Aethylred", "lcgdm", "yguenane", "AlexCline", "proletaryo", "spuder", "ispavailability", "jbussdieker", "jdowning"]}, "authors.last month": {"id": [2249095, 2249923, 2249867, 2249951, 2249092, 2249112, 2249949, 2249569, 2249165, 2249150, 2249953, 2249519, 2249287, 2249752, 2249400, 2249512, 2249560, 2249955, 2249954, 2249389, 2249587, 2249156, 2249271, 2249118, 2249978, 2249320, 2249965, 2249169, 2249273, 2249917, 2249977, 2249240, 2249677, 2249821, 2249144, 2249825, 2249215, 2249904, 2249237, 2249963, 2249136, 2249956, 2249919, 2249441, 2249945, 2249483, 2249776, 2249167, 2249373, 2249160], "releases": [24, 20, 20, 15, 14, 13, 13, 13, 12, 10, 8, 7, 7, 7, 7, 6, 6, 6, 6, 6, 5, 5, 5, 5, 5, 5, 5, 4, 4, 4, 4, 4, 4, 4, 4, 3, 3, 3, 3, 3, 3, 3, 3, 3, 3, 3, 3, 2, 2, 2], "username": ["maestrodev", "BradChesney79", "ceritsc", "herculesteam", "puppetlabs", "garethr", "jgazeley", "jriviere", "ghoneycutt", "theforeman", "velaluqa", "leoc", "mjhas", "pauloconnor", "tracywebtech", "hardening", "krakatoa", "lesaux", "ringingliberty", "spantree", "aco", "biemond", "flakrat", "opentable", "ph05365", "thbe", "tompurl", "arioch", "computology", "deversus", "diskstats", "mkrakowitzer", "oscerd", "rfletcher", "sbadia", "jlcox", "jlondon", "jpopelka", "lbetz", "lightoze", "mayflower", "rjbalest", "sharumpe", "stbenjam", "stevenmerrill", "wdijkerman", "xdrum", "badgerious", "brainsware", "camptocamp"]}, "authors.last year": {"id": [2249092, 2249093, 2249095, 2249156, 2249165, 2249270, 2249103, 2249173, 2249278, 2249266, 2249101, 2249112, 2249160, 2249342, 2249456, 2249352, 2249118, 2249282, 2249790, 2249400, 2249150, 2249262, 2249181, 2249242, 2249569, 2249180, 2249696, 2249544, 2249281, 2249169, 2249109, 2249152, 2249126, 2249147, 2249105, 2249120, 2249560, 2249427, 2249376, 2249320, 2249204, 2249306, 2249923, 2249210, 2249248, 2249211, 2249131, 2249192, 2249651, 2249389], "releases": [311, 248, 241, 131, 128, 111, 94, 89, 67, 64, 62, 59, 57, 56, 56, 55, 51, 47, 47, 45, 44, 42, 41, 35, 33, 32, 31, 30, 29, 28, 27, 27, 26, 26, 26, 26, 25, 25, 25, 25, 25, 24, 22, 22, 22, 22, 22, 22, 21, 21], "username": ["puppetlabs", "example42", "maestrodev", "biemond", "ghoneycutt", "pennycoders", "thias", "evenup", "ptomulik", "jhoblitt", "saz", "garethr", "camptocamp", "alkivi", "skoblenick", "leonardothibes", "opentable", "viirya", "vlshch", "tracywebtech", "theforeman", "inkblot", "hajee", "spuder", "jriviere", "arusso", "gajdaw", "abstractit", "Aethylred", "arioch", "fiddyspence", "netmanagers", "BoxUpp", "jdowning", "stankevich", "willdurand", "krakatoa", "KyleAnderson", "lcgdm", "thbe", "treydock", "desalvo", "BradChesney79", "conzar", "dmexe", "huit", "pdxcat", "zleslie", "markea", "spantree"]}}