{"actions": 277089, "added_lines": 16946413.0, "added_lines_30": 250584, "added_lines_365": 5980464, "added_lines_7": 2673, "authors": 1346, "authors_30": 120, "authors_365": 684, "authors_7": 50, "avg_commits_author": 35.6014, "avg_commits_month": 421.8125, "avg_files_author": 73.5448, "avg_files_month": 871.375, "branches": 166, "commits": 47243, "commits_30": 746, "commits_365": 11018, "commits_7": 112, "committers": 1107, "core": 62, "diff_netadded_lines_30": 16296, "diff_netadded_lines_365": 2100642, "diff_netadded_lines_7": -189959, "diff_netauthors_30": -13, "diff_netauthors_365": 146, "diff_netauthors_7": -5, "diff_netcommits_30": -128, "diff_netcommits_365": 219, "diff_netcommits_7": -17, "diff_netfiles_30": -1772, "diff_netfiles_365": -19075, "diff_netfiles_7": -516, "diff_netremoved_lines_30": 18206, "diff_netremoved_lines_365": -968640, "diff_netremoved_lines_7": -188121, "files": 97594, "files_30": 2474, "files_365": 28683, "files_7": 149, "first_date": "2005-04-13", "last_date": "2014-09-12", "occasional": 1074, "percentage_added_lines_30": 6, "percentage_added_lines_365": 54, "percentage_added_lines_7": 98, "percentage_authors_30": 9, "percentage_authors_365": 27, "percentage_authors_7": 9, "percentage_commits_30": 14, "percentage_commits_365": 2, "percentage_commits_7": 13, "percentage_files_30": 41, "percentage_files_365": 39, "percentage_files_7": 77, "percentage_removed_lines_30": 8, "percentage_removed_lines_365": 20, "percentage_removed_lines_7": 99, "regular": 191, "removed_lines": 12499763.0, "removed_lines_30": 240655, "removed_lines_365": 3784365, "removed_lines_7": 1022, "repositories": 193, "type": "git", "url": "git://github.com/puppetlabs/puppetlabs_spec_helper.git"}