{"diff_netcommits_365":202,"percentage_commits_365":1,"commits":39163,"first_date":"2005-04-13","last_date":"2013-12-19","committers":808,"authors":1017,"files":80014,"branches":101,"repositories":193,"actions":231401,"added_lines":11822527,"removed_lines":9259553,"avg_commits_month":376.5673,"avg_files_month":769.3654,"avg_commits_author":38.8137,"avg_files_author":79.3003,"url":"git://github.com/puppetlabs/puppetlabs-slidekit.git","type":"git","commits_7":275,"authors_7":53,"files_7":749,"added_lines_7":134263,"removed_lines_7":131437,"commits_14":511,"authors_14":76,"files_14":1046,"added_lines_14":258117,"removed_lines_14":252830,"commits_30":1078,"authors_30":115,"files_30":1891,"added_lines_30":420663,"removed_lines_30":265838,"commits_60":2373,"authors_60":193,"files_60":3007,"added_lines_60":461228,"removed_lines_60":289727,"commits_90":3946,"authors_90":272,"files_90":4641,"added_lines_90":833847,"removed_lines_90":524480,"commits_180":8228,"authors_180":426,"files_180":14642,"added_lines_180":2128141,"removed_lines_180":1429789,"commits_365":15608,"authors_365":600,"files_365":48175,"added_lines_365":4025951,"removed_lines_365":5223109,"commits_730":31065,"authors_730":815,"files_730":61633,"added_lines_730":5952286,"removed_lines_730":5762055,"core":49,"regular":141,"occasional":819,"diff_netcommits_30":-98,"percentage_commits_30":11,"diff_netcommits_7":11,"percentage_commits_7":6,"diff_netauthors_365":235,"percentage_authors_365":64,"diff_netauthors_30":-23,"percentage_authors_30":16,"diff_netauthors_7":3,"percentage_authors_7":6}