{"asenders": 87, "asenders_30": 15, "asenders_365": 67, "asenders_7": 4, "asent": 173, "asent_30": 28, "asent_365": 135, "asent_7": 7, "csenders": 35, "csenders_30": 4, "csenders_365": 30, "csenders_7": 3, "csent": 67, "csent_30": 6, "csent_365": 55, "csent_7": 5, "diff_netasenders_30": -7, "diff_netasenders_365": 43, "diff_netasenders_7": -3, "diff_netasent_30": -3, "diff_netasent_365": 100, "diff_netasent_7": -3, "diff_netcsenders_30": 3, "diff_netcsenders_365": 23, "diff_netcsenders_7": 3, "diff_netcsent_30": 5, "diff_netcsent_365": 43, "diff_netcsent_7": 5, "diff_netparticipants_30": 3, "diff_netparticipants_365": 237, "diff_netparticipants_7": -3, "diff_netqsenders_30": -6, "diff_netqsenders_365": 72, "diff_netqsenders_7": -3, "diff_netqsent_30": -8, "diff_netqsent_365": 90, "diff_netqsent_7": -2, "first_date": "2012-10-26", "last_date": "2014-12-20", "participants": 1414, "participants_30": 124, "participants_365": 886, "participants_7": 34, "percentage_asenders_30": 31, "percentage_asenders_365": 179, "percentage_asenders_7": 42, "percentage_asent_30": 9, "percentage_asent_365": 285, "percentage_asent_7": 30, "percentage_csenders_30": 300, "percentage_csenders_365": 328, "percentage_csenders_7": 0, "percentage_csent_30": 500, "percentage_csent_365": 358, "percentage_csent_7": 0, "percentage_participants_30": 2, "percentage_participants_365": 36, "percentage_participants_7": 8, "percentage_qsenders_30": 26, "percentage_qsenders_365": 257, "percentage_qsenders_7": 42, "percentage_qsent_30": 27, "percentage_qsent_365": 300, "percentage_qsent_7": 28, "qsenders": 127, "qsenders_30": 17, "qsenders_365": 100, "qsenders_7": 4, "qsent": 151, "qsent_30": 21, "qsent_365": 120, "qsent_7": 5}