{"changed": 447, "changed_30": 120, "changed_365": 408, "changed_7": 2, "changers": 46, "changers_30": 11, "changers_365": 41, "changers_7": 2, "closed": 151, "closed_30": 16, "closed_365": 131, "closed_7": 0, "closers": 5, "closers_30": 2, "closers_365": 5, "closers_7": 0, "diff_netchanged_30": -24, "diff_netchanged_365": 271, "diff_netchanged_7": -91, "diff_netchangers_30": 2, "diff_netchangers_365": 27, "diff_netchangers_7": -3, "diff_netclosed_30": 0, "diff_netclosed_365": 111, "diff_netclosed_7": -1, "diff_netclosers_30": -1, "diff_netclosers_365": 3, "diff_netclosers_7": -1, "diff_netopened_30": -24, "diff_netopened_365": 181, "diff_netopened_7": -1, "diff_netopeners_30": 2, "diff_netopeners_365": 39, "diff_netopeners_7": -1, "first_date": "2013-08-14", "last_date": "2014-12-27", "opened": 455, "opened_30": 8, "opened_365": 318, "opened_7": 2, "openers": 55, "openers_30": 7, "openers_365": 49, "openers_7": 2, "percentage_changed_30": 16, "percentage_changed_365": 197, "percentage_changed_7": 97, "percentage_changers_30": 22, "percentage_changers_365": 192, "percentage_changers_7": 60, "percentage_closed_30": 0, "percentage_closed_365": 555, "percentage_closed_7": 100, "percentage_closers_30": 33, "percentage_closers_365": 150, "percentage_closers_7": 100, "percentage_opened_30": 75, "percentage_opened_365": 132, "percentage_opened_7": 33, "percentage_openers_30": 40, "percentage_openers_365": 390, "percentage_openers_7": 33, "trackers": 1}