{"diff_netsenders_30": -186, "diff_netsenders_365": -221, "diff_netsenders_7": 65, "diff_netsent_30": -2993, "diff_netsent_365": -35122, "diff_netsent_7": 770, "first_date": "2007-12-02", "last_date": "2015-01-07", "percentage_senders_30": 20, "percentage_senders_365": 3, "percentage_senders_7": 38, "percentage_sent_30": 11, "percentage_sent_365": 10, "percentage_sent_7": 19, "repositories": 3, "senders": 20022, "senders_30": 722, "senders_365": 6006, "senders_7": 234, "sent": 1801946, "sent_30": 23180, "sent_365": 312599, "sent_7": 4628}