{"actions": 212, "added_lines": 4160.0, "added_lines_30": 37634, "added_lines_365": 5937236, "added_lines_7": 11095, "authors": 11, "authors_30": 0, "authors_365": 8, "authors_7": 0, "avg_commits_author": 9.3, "avg_commits_month": 3.5769, "avg_files_author": 4.7, "avg_files_month": 1.8077, "branches": 2, "commits": 93, "commits_30": 0, "commits_365": 19, "commits_7": 0, "committers": 11, "diff_netadded_lines_30": -304473, "diff_netadded_lines_365": 2031606, "diff_netadded_lines_7": 1386, "diff_netauthors_30": -3, "diff_netauthors_365": 2, "diff_netauthors_7": 0, "diff_netcommits_30": -4, "diff_netcommits_365": -16, "diff_netcommits_7": 0, "diff_netfiles_30": -5, "diff_netfiles_365": -5, "diff_netfiles_7": 0, "diff_netremoved_lines_30": -272310, "diff_netremoved_lines_365": -799045, "diff_netremoved_lines_7": -10265, "files": 47, "files_30": 0, "files_365": 14, "files_7": 0, "first_date": "2005-04-13", "last_date": "2014-12-13", "percentage_added_lines_30": 88, "percentage_added_lines_365": 52, "percentage_added_lines_7": 14, "percentage_authors_30": 100, "percentage_authors_365": 33, "percentage_authors_7": 0, "percentage_commits_30": 100, "percentage_commits_365": 45, "percentage_commits_7": 0, "percentage_files_30": 100, "percentage_files_365": 26, "percentage_files_7": 0, "percentage_removed_lines_30": 88, "percentage_removed_lines_365": 15, "percentage_removed_lines_7": 86, "removed_lines": 776.0, "removed_lines_30": 35715, "removed_lines_365": 4302032, "removed_lines_7": 1670, "repositories": 1}