{"actions": 58829, "added_lines": 1707738.0, "added_lines_30": 221313, "added_lines_365": 6511986, "added_lines_7": 8762, "authors": 421, "authors_30": 35, "authors_365": 165, "authors_7": 11, "avg_commits_author": 34.6787, "avg_commits_month": 128.1875, "avg_files_author": 21.3116, "avg_files_month": 78.7768, "branches": 15, "commits": 14357, "commits_30": 139, "commits_365": 2778, "commits_7": 25, "committers": 283, "diff_netadded_lines_30": 103058, "diff_netadded_lines_365": 3336305, "diff_netadded_lines_7": -21809, "diff_netauthors_30": 6, "diff_netauthors_365": 39, "diff_netauthors_7": -6, "diff_netcommits_30": -98, "diff_netcommits_365": 680, "diff_netcommits_7": -5, "diff_netfiles_30": 130, "diff_netfiles_365": -269, "diff_netfiles_7": -139, "diff_netremoved_lines_30": -181713, "diff_netremoved_lines_365": -24461, "diff_netremoved_lines_7": -40996, "files": 8823, "files_30": 413, "files_365": 2456, "files_7": 72, "first_date": "2005-04-13", "last_date": "2014-09-01", "percentage_added_lines_30": 87, "percentage_added_lines_365": 105, "percentage_added_lines_7": 71, "percentage_authors_30": 20, "percentage_authors_365": 30, "percentage_authors_7": 35, "percentage_commits_30": 41, "percentage_commits_365": 32, "percentage_commits_7": 16, "percentage_files_30": 45, "percentage_files_365": 9, "percentage_files_7": 65, "percentage_removed_lines_30": 76, "percentage_removed_lines_365": 0, "percentage_removed_lines_7": 94, "removed_lines": 1248384.0, "removed_lines_30": 56493, "removed_lines_365": 4165583, "removed_lines_7": 2472, "repositories": 1}