{"actions": 274, "added_lines": 3179.0, "added_lines_30": 46600, "added_lines_365": 6084936, "added_lines_7": 1060, "authors": 36, "authors_30": 4, "authors_365": 14, "authors_7": 1, "avg_commits_author": 3.5161, "avg_commits_month": 2.6585, "avg_files_author": 4.2258, "avg_files_month": 3.1951, "branches": 5, "commits": 109, "commits_30": 5, "commits_365": 35, "commits_7": 0, "committers": 36, "diff_netadded_lines_30": -271196, "diff_netadded_lines_365": 2332967, "diff_netadded_lines_7": -8237, "diff_netauthors_30": 3, "diff_netauthors_365": 0, "diff_netauthors_7": 1, "diff_netcommits_30": 5, "diff_netcommits_365": -8, "diff_netcommits_7": 0, "diff_netfiles_30": 7, "diff_netfiles_365": 68, "diff_netfiles_7": 0, "diff_netremoved_lines_30": -269986, "diff_netremoved_lines_365": -557311, "diff_netremoved_lines_7": -19083, "files": 131, "files_30": 7, "files_365": 96, "files_7": 0, "first_date": "2005-04-13", "last_date": "2014-12-02", "percentage_added_lines_30": 85, "percentage_added_lines_365": 62, "percentage_added_lines_7": 88, "percentage_authors_30": 300, "percentage_authors_365": 0, "percentage_authors_7": 0, "percentage_commits_30": 0, "percentage_commits_365": 18, "percentage_commits_7": 0, "percentage_files_30": 0, "percentage_files_365": 242, "percentage_files_7": 0, "percentage_removed_lines_30": 89, "percentage_removed_lines_365": 11, "percentage_removed_lines_7": 97, "removed_lines": 991.0, "removed_lines_30": 32285, "removed_lines_365": 4424012, "removed_lines_7": 545, "repositories": 1}