{"asenders.": {"id": [73, 99, 507, 2585, 664, 196, 292, 90, 485, 289, 111, 626, 692, 2355, 2326, 771, 373, 49, 539, 1637, 2444, 472, 631, 67, 1254, 39, 293, 748, 1458, 592, 446, 1018, 236, 981, 157, 423, 2149, 125, 375, 1121, 988, 1522, 1124, 1967, 2508, 1153, 698, 2615, 587, 21], "senders": ["ramindk", "llowder", "GregLarkin", "cbarbour", "spuder", "jonn", "Ancillas", "Stefan", "joshc", "lavaman", "domcleal", "rob", "golja", "tek0011", "rnelson0", "robrwo", "Red Cricket", "gh", "doc75", "WhatsARanjit", "hesco", "Pindish", "nibalizer", "reidmv", "spend", "binford2k", "Daenney", "lorcutt", "Renan Vicente", "ethrbunny", "Aleksey Timohin", "fnaard", "louismayorga", "rjc", "Tomasz Olszewski", "banjer", "khaefeli", "bmurts", "deric", "ffrank", "Martin Alfke", "mapa3m", "Mark Wunschel", "ptierno", "Chutki", "Gary Steven", "jaksky", "vmule", "Cardil", "nvpuppet"], "sent": [6768, 5945, 3504, 1848, 1802, 1675, 1136, 685, 456, 408, 384, 264, 252, 217, 216, 140, 120, 119, 108, 105, 102, 91, 85, 84, 63, 60, 60, 60, 58, 56, 55, 52, 44, 42, 42, 40, 40, 36, 36, 36, 36, 33, 32, 32, 30, 30, 30, 30, 28, 27]}, "asenders.last month": {"id": [2585, 507, 99, 2326, 111, 157, 472, 587, 67, 2849, 748, 1254, 1018, 1124, 2696, 2870, 49, 692, 2475, 2877, 2428, 2714, 2875, 2873, 2897, 2850, 2829, 1034, 2878, 2880, 1461, 988, 2639, 2861, 2854, 2921, 2917, 2922, 2906, 613, 584, 1221], "senders": ["cbarbour", "GregLarkin", "llowder", "rnelson0", "domcleal", "Tomasz Olszewski", "Pindish", "Cardil", "reidmv", "davidallanwright", "lorcutt", "spend", "fnaard", "Mark Wunschel", "StuartAbramsHumphries", "debajyoti", "gh", "golja", "xaz", "Kuldeeps", "Walid Shaari", "confiq", "Huy Le", "Kevin Corcoran", "mckownam", "PuppetNYC", "AmberW", "anthonyclark", "Antoine", "bombbomb", "joshbeard", "Martin Alfke", "mf", "ProfessorFate", "xlaufol", "dogfish182", "galser", "max", "Marc Runkel", "rilindo", "rlinehan", "steveax"], "sent": [561, 552, 82, 72, 48, 28, 26, 21, 18, 11, 10, 9, 8, 8, 8, 7, 7, 7, 6, 5, 5, 4, 4, 4, 4, 4, 3, 3, 3, 3, 3, 3, 3, 3, 3, 2, 2, 2, 1, 1, 1, 1]}, "asenders.last year": {"id": [73, 99, 2585, 664, 196, 507, 485, 90, 111, 2355, 2326, 626, 289, 292, 1637, 2444, 771, 472, 539, 1254, 373, 1458, 748, 49, 1018, 67, 2149, 692, 1522, 1121, 1967, 2508, 2615, 587, 592, 157, 2681, 1521, 1153, 1124, 2620, 2545, 1461, 21, 2625, 2497, 2720, 909, 2428, 39], "senders": ["ramindk", "llowder", "cbarbour", "spuder", "jonn", "GregLarkin", "joshc", "Stefan", "domcleal", "tek0011", "rnelson0", "rob", "lavaman", "Ancillas", "WhatsARanjit", "hesco", "robrwo", "Pindish", "doc75", "spend", "Red Cricket", "Renan Vicente", "lorcutt", "gh", "fnaard", "reidmv", "khaefeli", "golja", "mapa3m", "ffrank", "ptierno", "Chutki", "vmule", "Cardil", "ethrbunny", "Tomasz Olszewski", "Yeayu", "RobN", "Gary Steven", "Mark Wunschel", "schowdh", "keefbaker", "joshbeard", "nvpuppet", "bytwocoffee", "GLN", "inhumantsar", "timelord", "Walid Shaari", "binford2k"], "sent": [3008, 2255, 1848, 1122, 850, 648, 336, 305, 224, 217, 216, 216, 180, 168, 105, 102, 98, 91, 78, 63, 60, 58, 50, 49, 48, 42, 40, 35, 33, 32, 32, 30, 30, 28, 28, 28, 26, 25, 24, 24, 24, 22, 21, 21, 20, 20, 20, 20, 20, 18]}, "csenders.": {"id": [73, 507, 99, 292, 664, 2585, 196, 373, 2355, 90, 771, 502, 111, 698, 692, 626, 289, 2508, 485, 748, 2798, 375, 592, 2621, 1521, 236, 1121, 539, 212, 2681, 423, 1458, 426, 12, 2149, 2326, 2620, 525, 2284, 446, 125, 400, 126, 2388, 1967, 530, 631, 293, 496, 1707], "senders": ["ramindk", "GregLarkin", "llowder", "Ancillas", "spuder", "cbarbour", "jonn", "Red Cricket", "tek0011", "Stefan", "robrwo", "BaltoStar", "domcleal", "jaksky", "golja", "rob", "lavaman", "Chutki", "joshc", "lorcutt", "skirk", "deric", "ethrbunny", "jimsonpai", "RobN", "louismayorga", "ffrank", "doc75", "Luke", "Yeayu", "banjer", "Renan Vicente", "Cornellio", "ken", "khaefeli", "rnelson0", "schowdh", "stefanlasiewski", "thampi_lakshmi", "Aleksey Timohin", "bmurts", "PorkCharSui", "ThnikBriK", "DJB", "ptierno", "Anil", "nibalizer", "Daenney", "Andrey Adamovich", "lgbff"], "sent": [4794, 4512, 3649, 1672, 1292, 924, 775, 690, 558, 505, 476, 322, 304, 270, 252, 184, 180, 150, 108, 100, 96, 92, 88, 84, 80, 76, 71, 70, 70, 65, 64, 60, 54, 54, 48, 48, 48, 48, 48, 45, 45, 45, 45, 44, 44, 40, 40, 39, 36, 35]}, "csenders.last month": {"id": [507, 2585, 2798, 99, 373, 2681, 2326, 664, 2508, 2877, 111, 2825, 2849, 1521, 2714, 2917, 2875, 2870, 157, 2475, 2720, 2921, 2887, 2432, 2866, 2470, 2470, 2898, 2919, 2873, 2906, 2857, 1221, 2882, 2913], "senders": ["GregLarkin", "cbarbour", "skirk", "llowder", "Red Cricket", "Yeayu", "rnelson0", "spuder", "Chutki", "Kuldeeps", "domcleal", "pwattste", "davidallanwright", "RobN", "confiq", "galser", "Huy Le", "debajyoti", "Tomasz Olszewski", "xaz", "inhumantsar", "dogfish182", "manjunatha tn", "mtravis", "vineeth.linux", "Ath", "athreyavc@gmail.com", "bleecky", "davideagle", "Kevin Corcoran", "Marc Runkel", "nitins", "steveax", "sushi1992", "vinnu"], "sent": [360, 231, 84, 82, 45, 39, 36, 34, 30, 25, 16, 12, 11, 10, 8, 8, 8, 7, 7, 6, 5, 4, 4, 4, 3, 2, 2, 2, 2, 2, 1, 1, 1, 1, 1]}, "csenders.last year": {"id": [73, 664, 2585, 99, 507, 2355, 373, 771, 90, 698, 292, 2508, 111, 626, 196, 289, 2798, 2621, 1521, 485, 1121, 2681, 1458, 692, 502, 2149, 2326, 2620, 2284, 539, 525, 2388, 1967, 748, 1707, 400, 1250, 530, 2679, 2658, 2877, 592, 931, 2356, 1648, 2545, 1522, 1218, 2495, 2497], "senders": ["ramindk", "spuder", "cbarbour", "llowder", "GregLarkin", "tek0011", "Red Cricket", "robrwo", "Stefan", "jaksky", "Ancillas", "Chutki", "domcleal", "rob", "jonn", "lavaman", "skirk", "jimsonpai", "RobN", "joshc", "ffrank", "Yeayu", "Renan Vicente", "golja", "BaltoStar", "khaefeli", "rnelson0", "schowdh", "thampi_lakshmi", "doc75", "stefanlasiewski", "DJB", "ptierno", "lorcutt", "lgbff", "PorkCharSui", "Adam Ryczkowski", "Anil", "Glueon", "abhishekb", "Kuldeeps", "ethrbunny", "kemra102", "Naftuli Tzvi Kay", "yaplej", "keefbaker", "mapa3m", "AronR", "Derongan", "GLN"], "sent": [1974, 935, 924, 820, 720, 558, 360, 280, 230, 190, 152, 150, 144, 144, 125, 102, 96, 84, 80, 72, 69, 65, 60, 56, 49, 48, 48, 48, 48, 46, 45, 44, 44, 40, 35, 35, 32, 32, 30, 26, 25, 24, 24, 24, 24, 22, 21, 20, 20, 20]}, "participants.": {"id": [2538794, 273, 2513933, 2512111, 2518660, 2511610, 2514659, 2512127, 2516315, 338, 2546351, 2516459, 62, 2545595, 2545895, 2533436, 20, 788, 64, 2539389, 2547358, 2546100, 2511830, 2545703, 2545668, 2511980, 2515104, 2511662, 2545603, 2548026, 2511470, 2512064, 2519497, 2545620, 2525333, 2548428, 2547360, 2511475, 2545958, 2547798, 2545741, 1531, 2521641, 2544120, 2546368, 2511483, 2545838, 2532719, 1251, 2546345], "messages_sent": [12455, 9922, 8040, 3774, 2864, 2805, 2475, 1364, 1335, 1205, 1020, 812, 688, 620, 609, 588, 564, 511, 448, 288, 216, 200, 200, 195, 188, 187, 186, 180, 170, 156, 140, 136, 136, 136, 133, 132, 132, 130, 130, 130, 128, 126, 117, 115, 110, 107, 104, 104, 102, 100], "name": ["ramindk", "llowder", "GregLarkin", "spuder", "Ancillas", "cbarbour", "jonn", "tek0011", "Red Cricket", "Stefan", "Chutki", "robrwo", "domcleal", "jaksky", "BaltoStar", "lavaman", "joshc", "golja", "rob", "rnelson0", "jimsonpai", "lorcutt", "ethrbunny", "Pindish", "doc75", "hesco", "louismayorga", "deric", "RobN", "Yeayu", "nibalizer", "khaefeli", "banjer", "thampi_lakshmi", "gh", "skirk", "schowdh", "Luke", "Aleksey Timohin", "abhishekb", "Joseph Carlos", "Renan Vicente", "Cornellio", "WhatsARanjit", "keefbaker", "ffrank", "Anil", "kemra102", "Daenney", "GLN"]}, "participants.last month": {"id": [2513933, 2511610, 2546351, 273, 2539389, 2548428, 2516315, 2545703, 62, 2548766, 2548026, 2546129, 2549002, 2512111, 2520804, 2548938, 2512097, 2516998, 2549273, 2545603, 2539059, 2546335, 2538375, 2548981, 2546373, 2549370, 2546100, 2546303, 2545609, 2545965, 2535815, 2532719, 2549391, 668, 2549191, 2548982, 2525333, 788, 2548853, 1427, 2549000, 2548855, 2548882, 2548999, 2549064, 2530758, 2546330, 2511554, 2549063, 2549392], "messages_sent": [912, 792, 210, 164, 120, 96, 75, 65, 64, 55, 52, 42, 35, 34, 28, 28, 27, 21, 20, 20, 18, 18, 18, 16, 12, 12, 10, 10, 9, 8, 8, 8, 8, 8, 8, 8, 7, 7, 6, 6, 6, 6, 6, 6, 6, 5, 5, 4, 4, 4], "name": ["GregLarkin", "cbarbour", "Chutki", "llowder", "rnelson0", "skirk", "Red Cricket", "Pindish", "domcleal", "davidallanwright", "Yeayu", "Tomasz Olszewski", "Kuldeeps", "spuder", "Cardil", "debajyoti", "GeneBean", "supriya", "confiq", "RobN", "reidmv", "xaz", "pwattste", "Huy Le", "umairch", "galser", "lorcutt", "Cesar Sturion", "spend", "Mark Wunschel", "mtravis", "kemra102", "dogfish182", "fnaard", "mckownam", "StuartAbramsHumphries", "gh", "golja", "ProfessorFate", "Kevin Corcoran", "bombbomb", "xlaufol", "vineeth.linux", "Antoine", "manjunatha tn", "inhumantsar", "Walid Shaari", "pascal", "simpleit", "davideagle"]}, "participants.last year": {"id": [2538794, 273, 2511610, 2512111, 2513933, 2512127, 2546351, 2514659, 2516315, 338, 2516459, 20, 2545595, 62, 64, 2518660, 2539389, 2533436, 2547358, 2511980, 2545703, 2545603, 2548026, 2512064, 2545620, 2547360, 2548428, 2547798, 1531, 2545668, 2544120, 2546368, 2511483, 2546100, 2546345, 2532719, 788, 2545838, 2512109, 2545895, 2512032, 2546303, 1623, 2511830, 2522886, 2511803, 2547382, 2548766, 2545609, 2538010], "messages_sent": [5123, 3075, 2805, 2278, 1368, 1364, 1020, 975, 705, 535, 504, 408, 400, 368, 360, 320, 288, 282, 216, 187, 182, 170, 156, 136, 136, 132, 132, 130, 126, 124, 115, 110, 101, 100, 100, 96, 91, 80, 77, 77, 76, 70, 69, 68, 68, 68, 66, 66, 63, 60], "name": ["ramindk", "llowder", "cbarbour", "spuder", "GregLarkin", "tek0011", "Chutki", "jonn", "Red Cricket", "Stefan", "robrwo", "joshc", "jaksky", "domcleal", "rob", "Ancillas", "rnelson0", "lavaman", "jimsonpai", "hesco", "Pindish", "RobN", "Yeayu", "khaefeli", "thampi_lakshmi", "schowdh", "skirk", "abhishekb", "Renan Vicente", "doc75", "WhatsARanjit", "keefbaker", "ffrank", "lorcutt", "GLN", "kemra102", "golja", "Anil", "lgbff", "BaltoStar", "ptierno", "Cesar Sturion", "stefanlasiewski", "ethrbunny", "DJB", "Adam Ryczkowski", "Glueon", "davidallanwright", "spend", "PorkCharSui"]}, "qsenders.": {"id": [73, 2508, 664, 2355, 373, 99, 698, 502, 771, 2621, 2658, 472, 718, 2444, 931, 2284, 2050, 2545, 236, 1521, 2681, 2497, 2620, 292, 592, 936, 375, 530, 2149, 426, 212, 2849, 1252, 2552, 748, 2679, 1990, 587, 2386, 400, 2585, 423, 446, 1707, 703, 704, 995, 730, 196, 1250], "senders": ["ramindk", "Chutki", "spuder", "tek0011", "Red Cricket", "llowder", "jaksky", "BaltoStar", "robrwo", "jimsonpai", "abhishekb", "Pindish", "Joseph Carlos", "hesco", "kemra102", "thampi_lakshmi", "Cesar Sturion", "keefbaker", "louismayorga", "RobN", "Yeayu", "GLN", "schowdh", "Ancillas", "ethrbunny", "GeneBean", "deric", "Anil", "khaefeli", "Cornellio", "Luke", "davidallanwright", "supriya", "umairch", "lorcutt", "Glueon", "msirbaug", "Cardil", "dmo54", "PorkCharSui", "cbarbour", "banjer", "Aleksey Timohin", "lgbff", "shyp", "mandm_zoom", "Arney", "asktbt", "jonn", "Adam Ryczkowski"], "sent": [893, 840, 680, 589, 525, 328, 320, 266, 196, 132, 91, 91, 88, 85, 72, 72, 70, 66, 66, 65, 65, 60, 60, 56, 56, 54, 52, 48, 48, 45, 45, 44, 42, 42, 40, 36, 36, 35, 35, 35, 33, 32, 30, 28, 28, 27, 25, 25, 25, 24]}, "qsenders.last month": {"id": [2508, 472, 2849, 373, 936, 1252, 2870, 2681, 2326, 2798, 2552, 2050, 1521, 2714, 931, 587, 157, 2825, 2475, 2877, 2583, 2875, 2897, 2432, 1098, 2888, 2878, 2880, 677, 2861, 2833, 2866, 2631, 2854, 2898, 2890, 2855, 2919, 2921, 2917, 1632, 2894, 2887, 2874, 2915, 2871, 2683, 2470, 2470, 2932], "senders": ["Chutki", "Pindish", "davidallanwright", "Red Cricket", "GeneBean", "supriya", "debajyoti", "Yeayu", "rnelson0", "skirk", "umairch", "Cesar Sturion", "RobN", "confiq", "kemra102", "Cardil", "Tomasz Olszewski", "pwattste", "xaz", "Kuldeeps", "Anandk", "Huy Le", "mckownam", "mtravis", "pascal", "simpleit", "Antoine", "bombbomb", "mlanghor", "ProfessorFate", "saswamy", "vineeth.linux", "whitmojm", "xlaufol", "bleecky", "br00tal", "brettcarr", "davideagle", "dogfish182", "galser", "Gibbs", "Layne", "manjunatha tn", "MOHAN", "Ravi", "talal234", "Thomas.Edgar", "Ath", "athreyavc@gmail.com", "burrito"], "sent": [180, 39, 33, 30, 27, 21, 14, 13, 12, 12, 12, 10, 10, 8, 8, 7, 7, 6, 6, 5, 4, 4, 4, 4, 4, 4, 3, 3, 3, 3, 3, 3, 3, 3, 2, 2, 2, 2, 2, 2, 2, 2, 2, 2, 2, 2, 2, 1, 1, 1]}, "qsenders.last year": {"id": [2508, 2355, 373, 664, 698, 73, 2621, 771, 2658, 472, 2444, 2284, 2050, 2545, 1521, 2681, 931, 2497, 2620, 718, 2149, 936, 2849, 1252, 2552, 530, 2679, 1990, 2386, 2585, 502, 1707, 1250, 2825, 2326, 2798, 1648, 2507, 995, 1318, 2393, 2498, 426, 592, 2634, 212, 400, 2560, 525, 587], "senders": ["Chutki", "tek0011", "Red Cricket", "spuder", "jaksky", "ramindk", "jimsonpai", "robrwo", "abhishekb", "Pindish", "hesco", "thampi_lakshmi", "Cesar Sturion", "keefbaker", "RobN", "Yeayu", "kemra102", "GLN", "schowdh", "Joseph Carlos", "khaefeli", "GeneBean", "davidallanwright", "supriya", "umairch", "Anil", "Glueon", "msirbaug", "dmo54", "cbarbour", "BaltoStar", "lgbff", "Adam Ryczkowski", "pwattste", "rnelson0", "skirk", "yaplej", "t-readyroc", "Arney", "RobertII", "louis", "Aykyu", "Cornellio", "ethrbunny", "t.shenhao", "Luke", "PorkCharSui", "stecino", "stefanlasiewski", "Cardil"], "sent": [840, 589, 285, 221, 210, 141, 132, 126, 91, 91, 85, 72, 70, 66, 65, 65, 64, 60, 60, 48, 48, 45, 44, 42, 42, 40, 36, 36, 35, 33, 28, 28, 24, 24, 24, 24, 24, 21, 20, 20, 19, 18, 18, 16, 16, 15, 15, 15, 15, 14]}}